MANIFEST.in
README.txt
setup.py
o2w/__init__.py
o2w_cms.egg-info/PKG-INFO
o2w_cms.egg-info/SOURCES.txt
o2w_cms.egg-info/dependency_links.txt
o2w_cms.egg-info/requires.txt
o2w_cms.egg-info/top_level.txt