Metadata-Version: 1.0
Name: o2w-cms
Version: 0.0.5
Summary: Base package for web creation
Home-page: http://www.o2w.es/
Author: José Sánchez Moreno
Author-email: jose@o2w.es
License: LICENSE.txt
Platform: UNKNOWN
